perseuspy/__init__.py
perseuspy/dependent_peptides.py
perseuspy/parameters.py
perseuspy/version.py
perseuspy/io/__init__.py
perseuspy/io/maxquant.py
perseuspy/io/perseus/__init__.py
perseuspy/io/perseus/matrix.py
perseuspy/io/perseus/network.py
perseuspy/test/__init__.py
perseuspy/test/test_dependent_peptides.py
perseuspy/test/test_io.py
perseuspy/test/test_io_network.py
perseuspy/test/test_networkx.py
perseuspy/test/test_parameters.py
perseuspy-0.3.9.dist-info/DESCRIPTION.rst
perseuspy-0.3.9.dist-info/METADATA
perseuspy-0.3.9.dist-info/RECORD
perseuspy-0.3.9.dist-info/WHEEL
perseuspy-0.3.9.dist-info/metadata.json
perseuspy-0.3.9.dist-info/top_level.txt
