Metadata-Version: 2.0
Name: perseuspy
Version: 0.3.9
Summary: Utilities for integrating python scripts into Perseus workflows
Home-page: http://www.github.com/jdrudolph/perseuspy
Author: Jan Rudolph
Author-email: jan.daniel.rudolph@gmail.com
License: MIT
Platform: UNKNOWN
Requires-Dist: networkx (>=2.1)
Requires-Dist: pandas (>=0.24.0)
